[  {    "type": "post",    "url": "/activate",    "title": "激活用户",    "version": "1.0.0",    "name": "Activate",    "group": "Auth",    "description": "<p>请求邮箱验证码后，可以进行用户激活</p>",    "parameter": {      "fields": {        "Parameter": [          {            "group": "Parameter",            "type": "String",            "optional": false,            "field": "email",            "description": "<p>电子邮箱</p>"          },          {            "group": "Parameter",            "type": "String",            "optional": false,            "field": "emailCode",            "description": "<p>电子邮箱收到的验证码</p>"          }        ]      }    },    "success": {      "examples": [        {          "title": "激活成功",          "content": "激活成功",          "type": "json"        }      ]    },    "error": {      "examples": [        {          "title": "邮箱地址未注册或已激活",          "content": "邮箱地址未注册或已激活",          "type": "json"        },        {          "title": "验证码无效",          "content": "验证码无效",          "type": "json"        }      ]    },    "filename": "app/controller/auth.js",    "groupTitle": "Auth"  },  {    "type": "post",    "url": "/login",    "title": "用户登录",    "version": "1.0.0",    "name": "Login",    "group": "Auth",    "description": "<p>用于请求用户登录过程，需要提交用户名和密码，部分情况需要用户识别验证码。</p> <p>设置密码尝试错误保护，超过三次密码尝试错误会要求用户输入验证码，验证码由 captchaData 字段以 svg 格式提供。</p> <p>设置邮箱验证机制，必须保证用户邮箱有效才允许用户登录。</p>",    "parameter": {      "fields": {        "Parameter": [          {            "group": "Parameter",            "type": "String",            "optional": false,            "field": "username",            "description": "<p>用户登录名（可能是用户名/电子邮箱/手机号码）</p>"          },          {            "group": "Parameter",            "type": "String",            "optional": false,            "field": "password",            "description": "<p>登录密码</p>"          },          {            "group": "Parameter",            "type": "String",            "optional": false,            "field": "captchaCode",            "description": "<p>验证码识别结果</p>"          }        ]      }    },    "success": {      "fields": {        "200": [          {            "group": "200",            "type": "String",            "optional": false,            "field": "needCaptcha",            "description": "<p>登录受到限制时（密码3次错误），\b该字段为 true</p>"          },          {            "group": "200",            "type": "String",            "optional": false,            "field": "captchaData",            "description": "<p>内容为 svg 格式的验证码图片</p>"          },          {            "group": "200",            "type": "Boolean",            "optional": false,            "field": "isAdmin",            "description": "<p>指示用户是否为站点管理员</p>"          },          {            "group": "200",            "type": "Boolean",            "optional": false,            "field": "isAuthor",            "description": "<p>指示用户是否具有文章编辑权限</p>"          },          {            "group": "200",            "type": "Boolean",            "optional": false,            "field": "postLoginUrl",            "description": "<p>登录后跳转的 URL - 由用户在配置文件中指定，用于前端站没有自行实现用户系统时，cms用户系统会在登录成功后自动跳转到该URL</p>"          },          {            "group": "200",            "type": "String",            "optional": false,            "field": "token",            "description": "<p>用户身份凭据</p>"          }        ]      }    },    "error": {      "fields": {        "400": [          {            "group": "400",            "type": "String",            "optional": false,            "field": "UsernameNotExist",            "description": "<p>用户名/邮箱地址/手机号码不存在</p>"          },          {            "group": "400",            "type": "String",            "optional": false,            "field": "UserNotActivated",            "description": "<p>用户未激活</p>"          },          {            "group": "400",            "type": "String",            "optional": false,            "field": "PasswordError",            "description": "<p>密码错误</p>"          }        ]      }    },    "filename": "app/controller/auth.js",    "groupTitle": "Auth"  },  {    "type": "post",    "url": "/reset-password",    "title": "重置密码",    "version": "1.0.0",    "name": "PasswordReset",    "group": "Auth",    "description": "<p>请求邮箱验证码后，可以进行密码重置</p>",    "parameter": {      "fields": {        "Parameter": [          {            "group": "Parameter",            "type": "String",            "optional": false,            "field": "email",            "description": "<p>电子邮箱</p>"          },          {            "group": "Parameter",            "type": "String",            "optional": false,            "field": "emailCode",            "description": "<p>电子邮箱收到的验证码</p>"          },          {            "group": "Parameter",            "type": "String",            "optional": false,            "field": "newPassword",            "description": "<p>新的密码</p>"          }        ]      }    },    "success": {      "examples": [        {          "title": "密码重置成功",          "content": "密码重置成功",          "type": "json"        }      ]    },    "error": {      "examples": [        {          "title": "邮箱地址未注册",          "content": "邮箱地址未注册",          "type": "json"        },        {          "title": "验证码无效",          "content": "验证码无效",          "type": "json"        }      ]    },    "filename": "app/controller/auth.js",    "groupTitle": "Auth"  },  {    "type": "post",    "url": "/request-verify",    "title": "请求邮箱激活验证",    "version": "1.0.0",    "name": "RequestVerify",    "group": "Auth",    "description": "<p>在进行用户激活和重置密码操作之前，需要调用该接口。 调用成功后，用户会收到验证码。</p>",    "parameter": {      "fields": {        "Parameter": [          {            "group": "Parameter",            "type": "String",            "optional": false,            "field": "email",            "description": "<p>电子邮箱</p>"          }        ]      }    },    "success": {      "examples": [        {          "title": "邮件已发送，请注意查收",          "content": "邮件已发送，请注意查收",          "type": "json"        }      ]    },    "error": {      "examples": [        {          "title": "电子邮箱未注册，请检查",          "content": "电子邮箱未注册，请检查",          "type": "json"        },        {          "title": "验证请求频率过高，请1分钟后重试",          "content": "验证请求频率过高，请1分钟后重试",          "type": "json"        }      ]    },    "filename": "app/controller/auth.js",    "groupTitle": "Auth"  },  {    "type": "post",    "url": "/signup",    "title": "用户注册",    "version": "1.0.0",    "name": "SignUp",    "group": "Auth",    "description": "<p>注册新用户</p>",    "parameter": {      "fields": {        "Parameter": [          {            "group": "Parameter",            "type": "String",            "optional": false,            "field": "username",            "description": "<p>用户名</p>"          },          {            "group": "Parameter",            "type": "String",            "optional": false,            "field": "password",            "description": "<p>登录密码</p>"          },          {            "group": "Parameter",            "type": "String",            "optional": false,            "field": "passwordConfirm",            "description": "<p>密码确认（为了前端逻辑尽可能简单，直接后端实现）</p>"          },          {            "group": "Parameter",            "type": "String",            "optional": false,            "field": "email",            "description": "<p>电子邮箱</p>"          },          {            "group": "Parameter",            "type": "String",            "optional": false,            "field": "phoneNumber",            "description": "<p>手机号码</p>"          }        ]      }    },    "success": {      "examples": [        {          "title": "注册成功",          "content": "注册成功",          "type": "json"        }      ]    },    "error": {      "examples": [        {          "title": "用户名已占用，请更换",          "content": "用户名已占用，请更换",          "type": "json"        },        {          "title": "用户名格式不合法",          "content": "用户名格式不合法",          "type": "json"        },        {          "title": "密码长度小于8位，请重新设置",          "content": "密码长度小于8位，请重新设置",          "type": "json"        },        {          "title": "两次密码输入不一致",          "content": "两次密码输入不一致",          "type": "json"        },        {          "title": "电子邮箱格式不正确，请检查",          "content": "电子邮箱格式不正确，请检查",          "type": "json"        },        {          "title": "电子邮箱地址已被注册，请更换",          "content": "电子邮箱地址已被注册，请更换",          "type": "json"        }      ]    },    "filename": "app/controller/auth.js",    "groupTitle": "Auth"  }]
